codegreen/__init__.py
codegreen/main.py
codegreen/fecom/README.md
codegreen/fecom/__init__.py
codegreen/fecom/experiment/__init__.py
codegreen/fecom/experiment/analysis.py
codegreen/fecom/experiment/data.py
codegreen/fecom/experiment/experiment_kinds.py
codegreen/fecom/experiment/experiments.py
codegreen/fecom/experiment/plot.py
codegreen/fecom/experiment/rq1_analysis.py
codegreen/fecom/experiment/run.py
codegreen/fecom/measurement/README.md
codegreen/fecom/measurement/__init__.py
codegreen/fecom/measurement/cpu_temperature.py
codegreen/fecom/measurement/execution.py
codegreen/fecom/measurement/idle_stats.py
codegreen/fecom/measurement/measurement_config.py
codegreen/fecom/measurement/measurement_parse.py
codegreen/fecom/measurement/stable_check.py
codegreen/fecom/measurement/start_measurement.py
codegreen/fecom/measurement/utilities.py
codegreen/fecom/measurement/out/cpu_temperature.txt
codegreen/fecom/measurement/out/execution_log.txt
codegreen/fecom/measurement/out/nvidia_smi.txt
codegreen/fecom/measurement/out/perf.txt
codegreen/fecom/measurement/out/start_times.txt
codegreen/fecom/patching/README.md
codegreen/fecom/patching/__init__.py
codegreen/fecom/patching/client.log
codegreen/fecom/patching/method_level_patch_imports.py
codegreen/fecom/patching/method_level_script_patcher.py
codegreen/fecom/patching/patching_config.py
codegreen/fecom/patching/project_level_patch_imports.py
codegreen/fecom/patching/project_level_script_patcher.py
codegreen/fecom/patching/repo_patching.py
codegreen/utils/__init__.py
codegreen/utils/metadata.py
codegreen-0.1.32.dist-info/entry_points.txt
codegreen-0.1.32.dist-info/LICENSE
codegreen-0.1.32.dist-info/WHEEL
codegreen-0.1.32.dist-info/METADATA
codegreen-0.1.32.dist-info/RECORD
