Metadata-Version: 2.1
Name: codegreen
Version: 0.1.32
Summary: Codegreen package!
Author-email: Saurabhsingh Rajput <saurabh@dal.ca>
Classifier: License :: OSI Approved :: Apache Software License
Requires-Dist: typer>=0.9
Requires-Dist: GitPython
Requires-Dist: rich
Requires-Dist: tensorflow>=2.10
Requires-Dist: numpy>=1.23
Requires-Dist: pandas==1.5.3
Requires-Dist: matplotlib==3.7.0
Requires-Dist: psutil==5.9.5
Requires-Dist: nbformat
